nonebot_plugin_gshisbanner/__init__.py
nonebot_plugin_gshisbanner/adapters/__init__.py
nonebot_plugin_gshisbanner/adapters/ob11.py
nonebot_plugin_gshisbanner/adapters/red.py
nonebot_plugin_gshisbanner/alias.py
nonebot_plugin_gshisbanner/api.py
nonebot_plugin_gshisbanner/config.py
nonebot_plugin_gshisbanner/constant.py
nonebot_plugin_gshisbanner/deal.py
nonebot_plugin_gshisbanner/deal_json.py
nonebot_plugin_gshisbanner/draw.py
nonebot_plugin_gshisbanner/fonts/misans.ttf
nonebot_plugin_gshisbanner/model.py
nonebot_plugin_gshisbanner/send.py
nonebot_plugin_gshisbanner/start.py
nonebot_plugin_gshisbanner-1.3.2.dist-info/LICENSE
nonebot_plugin_gshisbanner-1.3.2.dist-info/METADATA
nonebot_plugin_gshisbanner-1.3.2.dist-info/WHEEL
nonebot_plugin_gshisbanner-1.3.2.dist-info/RECORD
