Metadata-Version: 2.1
Name: nonebot-plugin-gshisbanner
Version: 1.3.2
Summary: Nonebot2查询原神历史卡池小插件
License: MIT
Author: forchannot
Author-email: yy320206@gmail.com
Requires-Python: >=3.8,<4.0
Classifier: License :: OSI Approved :: MIT License
Classifier: Programming Language :: Python :: 3
Classifier: Programming Language :: Python :: 3.8
Classifier: Programming Language :: Python :: 3.9
Classifier: Programming Language :: Python :: 3.10
Classifier: Programming Language :: Python :: 3.11
Classifier: Programming Language :: Python :: 3.12
Requires-Dist: httpx (>=0.20.0,<1.0.0)
Requires-Dist: nonebot-plugin-send-anything-anywhere (>=0.3.1)
Requires-Dist: nonebot2 (>=2.1.0,<3.0.0)
Requires-Dist: pydantic (>=1.10.0,<2.0.0)
